blablabla/__init__.py
blablabla/actions.py
blablabla/orchestrator.py
blablabla/start_all.py
blablabla/typing_server.py
blablabla/whisper_online.py
blablabla/whisper_server.py
blablabla-0.0.16.dist-info/LICENSE
blablabla-0.0.16.dist-info/METADATA
blablabla-0.0.16.dist-info/WHEEL
blablabla-0.0.16.dist-info/RECORD
