Metadata-Version: 2.1
Name: blablabla
Version: 0.0.16
Summary: A simple application to enable voice activated chatbot
Home-page: https://github.com/oozut/blablabla
License: Apache-2.0
Keywords: faster-whisper,transcription,didaction
Author: Guillaume Cadot
Author-email: guillaume.cadot.1990@gmail.com
Requires-Python: >=3.10,<4.0
Classifier: Development Status :: 3 - Alpha
Classifier: Environment :: GPU :: NVIDIA CUDA :: 11.4
Classifier: Environment :: GPU :: NVIDIA CUDA :: 12 :: 12.2
Classifier: License :: OSI Approved :: Apache Software License
Classifier: Programming Language :: Python :: 3
Classifier: Programming Language :: Python :: 3.10
Classifier: Programming Language :: Python :: 3.11
Classifier: Programming Language :: Python :: 3.12
Requires-Dist: aiohttp (>=3.7.4,<4.0.0)
Requires-Dist: fastapi (>=0.111.0,<0.112.0)
Requires-Dist: faster-whisper (>=0.10.1)
Requires-Dist: keyboard (>=0.13.5,<0.14.0)
Requires-Dist: librosa (>=0.10.2,<0.11.0)
Requires-Dist: openai (>=1.30.4,<2.0.0)
Requires-Dist: orjson (>=3.6.5,<4.0.0)
Requires-Dist: pynput (>=1.7.3,<2.0.0)
Requires-Dist: pyperclip (>=1.8.2,<2.0.0)
Requires-Dist: pysoundfile (>=0.9,<0.10)
Requires-Dist: sounddevice (>=0.4.1,<0.5.0)
Requires-Dist: statesman (>=1.0,<2.0)
Requires-Dist: uvicorn (>=0.30.0,<0.31.0)
Project-URL: Repository, https://github.com/oozut/blablabla
